barely/__init__.py
barely/cli.py
barely/__pycache__/__init__.cpython-311.pyc
barely/__pycache__/__init__.cpython-39.pyc
barely/__pycache__/cli.cpython-311.pyc
barely/__pycache__/cli.cpython-39.pyc
barely/__pycache__/main.cpython-311.pyc
barely/__pycache__/main.cpython-39.pyc
barely/blueprints/blank/config.yaml
barely/blueprints/blog/COPY-TO-CONFIG.yaml
barely/blueprints/blog/metadata.yaml
barely/blueprints/blog/page.md
barely/blueprints/blog/blog/page.md
barely/blueprints/blog/blog/2022-04-01-building-a-blog-with-barely/post.md
barely/blueprints/blog/res/favicon.ico
barely/blueprints/blog/res/socialcover.png
barely/blueprints/blog/res/style.sass
barely/blueprints/blog/res/theme.js
barely/blueprints/blog/res/highlight/one-dark.css
barely/blueprints/blog/res/icons/facebook.svg
barely/blueprints/blog/res/icons/reddit.svg
barely/blueprints/blog/res/icons/share.svg
barely/blueprints/blog/res/icons/twitter.svg
barely/blueprints/blog/res/icons/ycombinator.svg
barely/blueprints/blog/rss/rss.md
barely/blueprints/blog/templates/overview.html
barely/blueprints/blog/templates/page.html
barely/blueprints/blog/templates/post.html
barely/blueprints/blog/templates/rss.html
barely/blueprints/blog/templates/tag.html
barely/blueprints/blog/templates/partials/base.html
barely/blueprints/blog/templates/partials/preview.html
barely/blueprints/blog/templates/partials/socials.html
barely/blueprints/default/config.yaml
barely/blueprints/default/metadata.yaml
barely/blueprints/default/page.md
barely/blueprints/default/res/favicon.ico
barely/blueprints/default/res/style.sass
barely/blueprints/default/templates/page.html
barely/blueprints/default/templates/partials/base.html
barely/cli/__pycache__/__init__.cpython-311.pyc
barely/cli/__pycache__/__init__.cpython-39.pyc
barely/cli/__pycache__/commands.cpython-311.pyc
barely/cli/__pycache__/commands.cpython-39.pyc
barely/cli/__pycache__/helpers.cpython-311.pyc
barely/cli/__pycache__/helpers.cpython-39.pyc
barely/common/__init__.py
barely-1.2.2.dist-info/LICENSE
barely-1.2.2.dist-info/METADATA
barely-1.2.2.dist-info/WHEEL
barely-1.2.2.dist-info/entry_points.txt
barely-1.2.2.dist-info/top_level.txt
barely-1.2.2.dist-info/RECORD
