Metadata-Version: 2.1
Name: barely
Version: 1.2.2
Summary: barely is a lightweight, but highly extensible static site generator written in pure python.
Home-page: https://notablog.io
Author: Charlotte Hartmann Paludo
Author-email: barely@charlotteharludo.com
License: GPL-3.0
Download-URL: https://github.com/charludo/barely/archive/refs/tags/v1.2.2.tar.gz
Keywords: static site generator,jinja2,markdown,web development,blog
Platform: UNKNOWN
Classifier: Development Status :: 5 - Production/Stable
Classifier: Intended Audience :: Developers
Classifier: Topic :: Text Processing :: Markup :: HTML
Classifier: Topic :: Text Processing :: General
Classifier: Topic :: Software Development :: Build Tools
Classifier: Topic :: Software Development
Classifier: License :: OSI Approved :: GNU General Public License v3 (GPLv3)
Classifier: Natural Language :: English
Classifier: Programming Language :: Python :: 3.9
Classifier: Environment :: Console
Classifier: Operating System :: OS Independent
Requires-Python: >=3.9.0
License-File: LICENSE
Requires-Dist: click>=8.0.0
Requires-Dist: click-default-group>=1.2.2
Requires-Dist: coloredlogs>=15.0.0
Requires-Dist: mock>=4.0.0
Requires-Dist: pyyaml>=5.3.0
Requires-Dist: watchdog>=2.0.0
Requires-Dist: pillow>=8.0.0
Requires-Dist: GitPython>=3.0.0
Requires-Dist: pygments>=2.5.0
Requires-Dist: libsass>=0.21.0
Requires-Dist: pysftp>=0.2.5
Requires-Dist: livereload>=2.5.0
Requires-Dist: binaryornot>=0.4.0
Requires-Dist: jinja2>=3.0.0
Requires-Dist: mistune>=2.0.0rc1
Requires-Dist: calmjs>=3.3.0
